fastpluggy_plugin/websocket_tool/__init__.py
fastpluggy_plugin/websocket_tool/config.py
fastpluggy_plugin/websocket_tool/plugin.py
fastpluggy_plugin/websocket_tool/register_handlers.py
fastpluggy_plugin/websocket_tool/ws_manager.py
fastpluggy_plugin/websocket_tool/extra_widget/__init__.py
fastpluggy_plugin/websocket_tool/extra_widget/async_registry.py
fastpluggy_plugin/websocket_tool/extra_widget/async_widget.py
fastpluggy_plugin/websocket_tool/extra_widget/async_worker.py
fastpluggy_plugin/websocket_tool/extra_widget/websocket_details_widget.py
fastpluggy_plugin/websocket_tool/notifiers/__init__.py
fastpluggy_plugin/websocket_tool/notifiers/websocket.py
fastpluggy_plugin/websocket_tool/routers/__init__.py
fastpluggy_plugin/websocket_tool/routers/admin.py
fastpluggy_plugin/websocket_tool/routers/info.py
fastpluggy_plugin/websocket_tool/routers/ws.py
fastpluggy_plugin/websocket_tool/schema/__init__.py
fastpluggy_plugin/websocket_tool/schema/ws_message.py
fastpluggy_plugin/websocket_tool/static/scripts.js
fastpluggy_plugin/websocket_tool/static/service-worker.js
fastpluggy_plugin/websocket_tool/static/websocket-client.js
fastpluggy_plugin/websocket_tool/templates/async_ws_wrapper.html.j2
fastpluggy_plugin/websocket_tool/templates/websocket_details.html.j2
fastpluggy_websocket_tool-0.1.24.dist-info/METADATA
fastpluggy_websocket_tool-0.1.24.dist-info/WHEEL
fastpluggy_websocket_tool-0.1.24.dist-info/entry_points.txt
fastpluggy_websocket_tool-0.1.24.dist-info/top_level.txt
fastpluggy_websocket_tool-0.1.24.dist-info/RECORD
