Metadata-Version: 2.4
Name: fastpluggy-websocket-tool
Version: 0.1.24
Summary: FastPluggy plugin for real-time WebSocket communication
Author: FastPluggy Team
Requires-Python: >=3.10
Requires-Dist: pydantic>=2.0.0
Requires-Dist: websockets>=11.0.3
Requires-Dist: fastpluggy-ui-tools>=0.0.5
Provides-Extra: client
Requires-Dist: websockets>=11.0.3; extra == "client"
